{"filename":"iroco.json","collections":[{"name":"clientes","data":[{"nif":"1","nombre":"Ivan","apellidos":"drogadicto","fechaNac":"2025-01-30T23:00:00.000Z","pasaporte":"1","direccion":"Calle rodolfo gutierrez moreno","email":"1","telefono":"1","firma":"1","ciudad":"Santo Tome","codPostal":"23311","expId":1,"fecha":"2025-01-25T15:40:33.116Z","meta":{"revision":1,"created":1737819633117,"version":0,"updated":1738689835774},"$loki":1},{"nif":"2","nombre":"Cubarsi","apellidos":"1","fechaNac":"2021-02-17T23:00:00.000Z","pasaporte":"2","direccion":"peñaflor 2","email":"2","telefono":"2","firma":"2","ciudad":"cazorla","codPostal":"23311","expId":2,"fecha":"2025-01-25T15:47:09.746Z","meta":{"revision":3,"created":1737820029748,"version":0,"updated":1738524360428},"$loki":2},{"nif":"asdasdasdasd","nombre":"asdasd","apellidos":"asdasdasd","fechaNac":"2025-02-03T23:00:00.000Z","pasaporte":"asdasdasd","direccion":"asdasdasd","email":"asdasdasd","telefono":"435345345","firma":"asdasasd","ciudad":"asdasdasd","codPostal":"324234","expId":2,"fecha":"2025-02-02T19:10:48.626Z","meta":{"revision":0,"created":1738523448628,"version":0},"$loki":3},{"nif":"ssdasd","nombre":"fffff","apellidos":"fffff","fechaNac":"2024-09-01T22:00:00.000Z","pasaporte":"asda","direccion":"fsdf","email":"3435345","telefono":"345","firma":"345345","ciudad":"sdfsd","codPostal":"45345","expId":2,"fecha":"2025-02-02T19:27:17.460Z","meta":{"revision":0,"created":1738524437460,"version":0},"$loki":4},{"nif":"kjh","nombre":"lkjh","apellidos":"ljkh","fechaNac":"2025-02-10T23:00:00.000Z","pasaporte":"klj","direccion":"hkj","email":"jh","telefono":"jhlk","firma":"jkh","ciudad":"hkj","codPostal":"hk","expId":6,"fecha":"2025-02-02T19:42:06.611Z","meta":{"revision":0,"created":1738525326611,"version":0},"$loki":5},{"nif":"cxbxcvxc","nombre":"bbbbbb","apellidos":"bbbbb","fechaNac":"2025-02-03T23:00:00.000Z","pasaporte":"bxcxcv","direccion":"xcvxc","email":"vccv","telefono":"nbmnbvm","firma":"cvbcvb","ciudad":"xcvxcv","codPostal":"xcbvmnbm","expId":6,"fecha":"2025-02-02T19:42:19.875Z","meta":{"revision":0,"created":1738525339876,"version":0},"$loki":6},{"nif":"dfgdfgdfg","nombre":"zxczxvcxbvn","apellidos":"dfghndfgh","fechaNac":"2025-02-05T23:00:00.000Z","pasaporte":"ghmbn","direccion":"cbvnv","email":"vzdfxc","telefono":"xczxc","firma":"cxg","ciudad":"zc","codPostal":"vzcxvzxcv","expId":6,"fecha":"2025-02-02T19:42:31.635Z","meta":{"revision":0,"created":1738525351635,"version":0},"$loki":7}],"idIndex":[1,2,3,4,5,6,7],"binaryIndices":{},"constraints":null,"uniqueNames":["nif"],"transforms":{},"objType":"clientes","dirty":false,"cachedIndex":null,"cachedBinaryIndex":null,"cachedData":null,"adaptiveBinaryIndices":true,"transactional":false,"cloneObjects":false,"cloneMethod":"parse-stringify","asyncListeners":false,"disableMeta":false,"disableChangesApi":true,"disableDeltaChangesApi":true,"autoupdate":false,"serializableIndices":true,"disableFreeze":true,"ttl":null,"maxId":7,"DynamicViews":[],"events":{"insert":[],"update":[],"pre-insert":[],"pre-update":[],"close":[],"flushbuffer":[],"error":[],"delete":[null],"warning":[null]},"changes":[],"dirtyIds":[]},{"name":"expedientes","data":[{"ref":"ejemplo asdakshdljkas hkajshdjka sh aljkshdkajsd","idGrupo":"1","fechaSalida":"2025-01-30T23:00:00.000Z","fecha":"2025-01-25T15:40:08.677Z","meta":{"revision":10,"created":1737819608679,"version":0,"updated":1738525496788},"$loki":1},{"ref":"ivan","idGrupo":"1","fechaSalida":"2025-01-30T23:00:00.000Z","fecha":"2025-01-25T15:44:50.534Z","contratCancel":true,"visado":true,"seguro":true,"aerolinea":true,"proforma":true,"contratViaje":true,"meta":{"revision":54,"created":1737819890536,"version":0,"updated":1738524452069},"$loki":2},{"ref":"ssss","idGrupo":"s","fechaSalida":"2025-02-17T23:00:00.000Z","fecha":"2025-02-02T19:39:42.356Z","contratCancel":true,"visado":true,"seguro":true,"aerolinea":true,"proforma":true,"contratViaje":true,"meta":{"revision":6,"created":1738525182349,"version":0,"updated":1738525363317},"$loki":6}],"idIndex":null,"binaryIndices":{},"constraints":null,"uniqueNames":["ref","$loki"],"transforms":{},"objType":"expedientes","dirty":false,"cachedIndex":null,"cachedBinaryIndex":null,"cachedData":null,"adaptiveBinaryIndices":true,"transactional":false,"cloneObjects":false,"cloneMethod":"parse-stringify","asyncListeners":false,"disableMeta":false,"disableChangesApi":true,"disableDeltaChangesApi":true,"autoupdate":false,"serializableIndices":true,"disableFreeze":true,"ttl":null,"maxId":6,"DynamicViews":[],"events":{"insert":[],"update":[],"pre-insert":[],"pre-update":[],"close":[],"flushbuffer":[],"error":[],"delete":[null],"warning":[null]},"changes":[],"dirtyIds":[]},{"name":"presupuestos","data":[{"ref":"asdasd","fecha":"2025-02-02T19:44:32.339Z","meta":{"revision":0,"created":1738525472339,"version":0},"$loki":1}],"idIndex":null,"binaryIndices":{},"constraints":null,"uniqueNames":["ref"],"transforms":{},"objType":"presupuestos","dirty":false,"cachedIndex":null,"cachedBinaryIndex":null,"cachedData":null,"adaptiveBinaryIndices":true,"transactional":false,"cloneObjects":false,"cloneMethod":"parse-stringify","asyncListeners":false,"disableMeta":false,"disableChangesApi":true,"disableDeltaChangesApi":true,"autoupdate":false,"serializableIndices":true,"disableFreeze":true,"ttl":null,"maxId":1,"DynamicViews":[],"events":{"insert":[],"update":[],"pre-insert":[],"pre-update":[],"close":[],"flushbuffer":[],"error":[],"delete":[null],"warning":[null]},"changes":[],"dirtyIds":[]}],"databaseVersion":1.5,"engineVersion":1.5,"autosave":true,"autosaveInterval":4000,"autosaveHandle":null,"throttledSaves":true,"options":{"autoload":true,"autosave":true,"autosaveInterval":4000,"serializationMethod":"normal","destructureDelimiter":"$<\n","recursiveWait":true,"recursiveWaitLimit":false,"recursiveWaitLimitDuration":2000,"started":1738689509858},"persistenceMethod":"fs","persistenceAdapter":null,"verbose":false,"events":{"init":[null],"loaded":[],"flushChanges":[],"close":[],"changes":[],"warning":[]},"ENV":"NODEJS"}